{ "root": [
    {
        "cid" : "0551",
        "cname" : "合肥",
        "list" : [
            {"value" : -1, "name" : "--请选择--"},
            {"value": 65, "name": "合肥瑞景"},
            {"value": 105, "name": "合肥百盛"},
            {"value": 171, "name": "合肥鼓楼"}]
    },
    {
        "cid" : "010",
        "cname" : "北京",
        "list" : [
            {"value" : -1, "name" : "--请选择--"},
            {"value": 31, "name": "北京汉光"},
            {"value": 12, "name": "北京百盛"},
            {"value": 14, "name": "北京双安"},
            {"value": 49, "name": "北京翠微"},
            {"value": 95, "name": "北京君太"},
            {"value": 109, "name": "北京太阳宫百盛"},
            {"value": 75, "name": "北京新光三越"},
            {"value": 56, "name": "北京新世界"},
            {"value": 17, "name": "北京崇光"},
            {"value": 28, "name": "北京王府井"},
            {"value": 233, "name": "北京大兴王府井"},
            {"value": 192, "name": "北京老佛爷"}]
    },
    {
        "cid" : "0591",
        "cname" : "福州",
        "list" : [
            {"value" : -1, "name" : "--请选择--"},
            {"value": 163, "name": "福州王府井"},
            {"value": 45, "name": "福州大洋"}]
    },
    {
        "cid" : "0931",
        "cname" : "兰州",
        "list" : [
        {"value": "135", "name": "兰州国芳"}]
    },
    {
        "cid" : "0769",
        "cname" : "东莞",
        "list" : [
        {"value": "179", "name": "东莞海雅"}]
    },
    {
        "cid" : "020",
        "cname" : "广州",
        "list" : [
            {"value" : -1, "name" : "--请选择--"},
            {"value": 46, "name": "广州友谊"},
            {"value": 87, "name": "广州友谊正佳"},
            {"value": 47, "name": "广州广百"},
            {"value": 93, "name": "广州中怡"},
            {"value": 104, "name": "广州天河城"}]
    },
    {
        "cid" : "0755",
        "cname" : "深圳",
        "list" : [
            {"value" : -1, "name" : "--请选择--"},
            {"value": 34, "name": "深圳茂业"},
            {"value": 164, "name": "深圳太阳百货"},
            {"value": 195, "name": "深圳海岸城"},
            {"value": 226, "name": "深圳东门茂业"}]
    },
    {
        "cid" : "0773",
        "cname" : "桂林",
        "list" : [
            {"value": 235, "name": "桂林微笑堂"}]
    },
    {
        "cid" : "0771",
        "cname" : "南宁",
        "list" : [
            {"value" : -1, "name" : "--请选择--"},
            {"value": 101, "name": "南宁梦之岛"},
            {"value": 108, "name": "南宁百盛"},
            {"value": 168, "name": "南宁万象城"}]
    },
    {
        "cid" : "0851",
        "cname" : "贵阳",
        "list" : [
            {"value" : -1, "name" : "--请选择--"},
            {"value": 62, "name": "贵阳国贸"},
            {"value": 72, "name": "贵阳星力"}]
    },
    {
        "cid" : "0310",
        "cname" : "邯郸",
        "list" : [
            {"value": 150, "name": "邯郸新世纪"}]
    },
    {
        "cid" : "0311",
        "cname" : "石家庄",
        "list" : [
            {"value" : -1, "name" : "--请选择--"},
            {"value": 66, "name": "石家庄北国"},
            {"value": 217, "name": "石家庄新百"}]
    },
    {
        "cid" : "0315",
        "cname" : "唐山",
        "list" : [
            {"value": 177, "name": "唐山百货大楼"}]
    },
    {
        "cid" : "0898",
        "cname" : "海口",
        "list" : [
            {"value": 238, "name": "海口望海国际"}]
    },
    {
        "cid" : "0379",
        "cname" : "洛阳",
        "list" : [
            {"value": 137, "name": "洛阳王府井"}]
    },
    {
        "cid" : "0371",
        "cname" : "郑州",
        "list" : [
            {"value" : -1, "name" : "--请选择--"},
            {"value": 38, "name": "郑州丹尼斯"},
            {"value": 77, "name": "郑州金博大"},
            {"value": 130, "name": "郑州丹尼斯花园店"}]
    },
    {
        "cid" : "0459",
        "cname" : "大庆",
        "list" : [
            {"value": 196, "name": "大庆新玛特"}]
    },
    {
        "cid" : "0451",
        "cname" : "哈尔滨",
        "list" : [
            {"value" : -1, "name" : "--请选择--"},
            {"value": 29, "name": "哈尔滨远大"},
            {"value": 90, "name": "哈尔滨松雷"},
            {"value": 214, "name": "哈尔滨百盛"}]
    },
    {
        "cid" : "0719",
        "cname" : "十堰",
        "list" : [
            {"value": 200, "name": "十堰人民商场"}]
    },
    {
        "cid" : "027",
        "cname" : "武汉",
        "list" : [
            {"value" : -1, "name" : "--请选择--"},
            {"value": 22, "name": "武汉广场"},
            {"value": 88, "name": "武汉群光"},
            {"value": 166, "name": "武汉大洋"},
            {"value": 219, "name": "武汉大洋光谷"}]
    },
    {
        "cid" : "0717",
        "cname" : "宜昌",
        "list" : [
            {"value": 139, "name": "宜昌国贸"}]
    },
    {
        "cid" : "0731",
        "cname" : "长沙",
        "list" : [
            {"value" : -1, "name" : "--请选择--"},
            {"value": 42, "name": "长沙平和堂"},
            {"value": 154, "name": "长沙平和堂东塘店"},
            {"value": 64, "name": "长沙王府井"}]
    },
    {
        "cid" : "0431",
        "cname" : "长春",
        "list" : [
            {"value" : -1, "name" : "--请选择--"},
            {"value": 30, "name": "长春卓展"},
            {"value": 89, "name": "长春欧亚"}]
    },
    {
        "cid" : "0432",
        "cname" : "吉林",
        "list" : [
            {"value": 213, "name": "吉林欧亚"}]
    },
    {
        "cid" : "0433",
        "cname" : "延吉",
        "list" : [
            {"value": 211, "name": "延吉百货"}]
    },
    {
        "cid" : "05122",
        "cname" : "常熟",
        "list" : [
            {"value": 234, "name": "常熟八佰伴"}]
    },
    {
        "cid" : "0519",
        "cname" : "常州",
        "list" : [
            {"value" : -1, "name" : "--请选择--"},
            {"value": 54, "name": "常州泰富"},
            {"value": 85, "name": "常州购物中心"}]
    },
    {
        "cid" : "0517",
        "cname" : "淮安",
        "list" : [
            {"value": 208, "name": "淮安金鹰"}]
    },
    {
        "cid" : "05101",
        "cname" : "江阴",
        "list" : [
            {"value": 157, "name": "江阴华地"}]
    },
    {
        "cid" : "05121",
        "cname" : "昆山",
        "list" : [
            {"value": 183, "name": "昆山商厦"}]
    },
    {
        "cid" : "025",
        "cname" : "南京",
        "list" : [
            {"value" : -1, "name" : "--请选择--"},
            {"value": 42, "name": "南京金鹰"},
            {"value": 154, "name": "南京大洋"},
            {"value": 154, "name": "南京金鹰珠江店"},
            {"value": 64, "name": "南京中央"}]
    },
    {
        "cid" : "0513",
        "cname" : "南通",
        "list" : [
            {"value": 149, "name": "南通文峰大世界"}]
    },
    {
        "cid" : "05120",
        "cname" : "苏州",
        "list" : [
            {"value": 41, "name": "苏州美罗"}]
    },
    {
        "cid" : "0523",
        "cname" : "泰州",
        "list" : [
            {"value": 159, "name": "泰州金鹰"}]
    },
    {
        "cid" : "05100",
        "cname" : "无锡",
        "list" : [
            {"value" : -1, "name" : "--请选择--"},
            {"value": 37, "name": "无锡百盛"},
            {"value": 92, "name": "无锡商业大厦"},
            {"value": 146, "name": "无锡八佰伴"}]
    },
    {
        "cid" : "0516",
        "cname" : "徐州",
        "list" : [
            {"value": 110, "name": "徐州金鹰"}]
    },
    {
        "cid" : "0515",
        "cname" : "盐城",
        "list" : [
            {"value": 136, "name": "盐城金鹰"}]
    },
    {
        "cid" : "0514",
        "cname" : "扬州",
        "list" : [
            {"value": 111, "name": "扬州金鹰"}]
    },
    {
        "cid" : "0510",
        "cname" : "宜兴",
        "list" : [
            {"value": 189, "name": "宜兴华地"}]
    },
    {
        "cid" : "0511",
        "cname" : "镇江",
        "list" : [
            {"value": 165, "name": "镇江八佰伴"}]
    },
    {
        "cid" : "0791",
        "cname" : "南昌",
        "list" : [
            {"value": 125, "name": "南昌百盛"}]
    },
    {
        "cid" : "0412",
        "cname" : "鞍山",
        "list" : [
            {"value": 107, "name": "鞍山百盛"}]
    },
    {
        "cid" : "0411",
        "cname" : "大连",
        "list" : [
            {"value" : -1, "name" : "--请选择--"},
            {"value": 25, "name": "大连麦凯乐"},
            {"value": 228, "name": "大连锦辉"}]
    },
    {
        "cid" : "024",
        "cname" : "沈阳",
        "list" : [
            {"value" : -1, "name" : "--请选择--"},
            {"value": 21, "name": "沈阳中兴"},
            {"value": 57, "name": "沈阳新玛特"},
            {"value": 67, "name": "沈阳卓展"},
            {"value": 161, "name": "沈阳新一城"}]
    },
    {
        "cid" : "0471",
        "cname" : "呼和浩特",
        "list" : [
            {"value": 118, "name": "呼和浩特维多利"}]
    },
    {
        "cid" : "0951",
        "cname" : "银川",
        "list" : [
            {"value": 143, "name": "银川新华"}]
    },
    {
        "cid" : "0971",
        "cname" : "西宁",
        "list" : [
            {"value": 141, "name": "西宁王府井"}]
    },
    {
        "cid" : "0534",
        "cname" : "德州",
        "list" : [
            {"value": 134, "name": "德州百货"}]
    },
    {
        "cid" : "0531",
        "cname" : "济南",
        "list" : [
            {"value": 80, "name": "济南银座"}]
    },
    {
        "cid" : "0539",
        "cname" : "临沂",
        "list" : [
            {"value": 143, "name": "临沂银座"}]
    },
    {
        "cid" : "0532",
        "cname" : "青岛",
        "list" : [
            {"value": 218, "name": "青岛麦凯乐"}]
    },
    {
        "cid" : "0631",
        "cname" : "威海",
        "list" : [
            {"value": 178, "name": "威海振华"}]
    },
    {
        "cid" : "0535",
        "cname" : "烟台",
        "list" : [
            {"value": 100, "name": "烟台振华"}]
    },
    {
        "cid" : "0533",
        "cname" : "淄博",
        "list" : [
            {"value": 188, "name": "淄博银座"}]
    },
    {
        "cid" : "0352",
        "cname" : "大同",
        "list" : [
            {"value": 203, "name": "大同百盛"}]
    },
    {
        "cid" : "0351",
        "cname" : "太原",
        "list" : [
            {"value" : -1, "name" : "--请选择--"},
            {"value": 71, "name": "太原华宇"},
            {"value": 98, "name": "太原百盛"}]
    },
    {
        "cid" : "029",
        "cname" : "西安",
        "list" : [
            {"value" : -1, "name" : "--请选择--"},
            {"value": 23, "name": "西安金花"},
            {"value": 76, "name": "西安金花高新"},
            {"value": 58, "name": "西安金鹰"},
            {"value": 170, "name": "西安开元"}]
    },
    {
        "cid" : "021",
        "cname" : "上海",
        "list" : [
            {"value" : -1, "name" : "--请选择--"},
            {"value": 1, "name": "上海太平洋徐汇店"},
            {"value": 4, "name": "上海梅龙镇"},
            {"value": 26, "name": "上海第一八佰伴"},
            {"value": 7, "name": "上海百盛"},
            {"value": 27, "name": "上海久光"},
            {"value": 8, "name": "上海东方商厦"},
            {"value": 94, "name": "上海新世界"},
            {"value": 115, "name": "上海巴黎春天"},
            {"value": 206, "name": "上海环贸广场"}]
    },
    {
        "cid" : "028",
        "cname" : "成都",
        "list" : [
            {"value" : -1, "name" : "--请选择--"},
            {"value": 48, "name": "成都王府井"},
            {"value": 78, "name": "成都伊势丹"},
            {"value": 119, "name": "成都太平洋天府"},
            {"value": 131, "name": "成都伊藤洋华堂(双楠店)"},
            {"value": 132, "name": "成都王府井2店"},
            {"value": 215, "name": "成都茂业"},
            {"value": 230, "name": "成都乐天"}]
    },
    {
        "cid" : "0816",
        "cname" : "绵阳",
        "list" : [
            {"value": 202, "name": "绵阳百盛"}]
    },
    {
        "cid" : "022",
        "cname" : "天津",
        "list" : [
            {"value" : -1, "name" : "--请选择--"},
            {"value": 18, "name": "天津伊势丹"},
            {"value": 40, "name": "天津友谊"},
            {"value": 60, "name": "天津远东"},
            {"value": 116, "name": "天津乐天"},
            {"value": 176, "name": "天津金元宝"},
            {"value": 227, "name": "天津百盛"}]
    },
    {
        "cid" : "0993",
        "cname" : "乌鲁木齐",
        "list" : [
            {"value" : -1, "name" : "--请选择--"},
            {"value": 106, "name": "乌鲁木齐天百"},
            {"value": 114, "name": "乌鲁木齐友好"},
            {"value": 172, "name": "乌鲁木齐百盛"}]
    },
    {
        "cid" : "0871",
        "cname" : "昆明",
        "list" : [
            {"value" : -1, "name" : "--请选择--"},
            {"value": 83, "name": "昆明金格"},
            {"value": 91, "name": "昆明百盛"}]
    },
    {
        "cid" : "0571",
        "cname" : "杭州",
        "list" : [
            {"value" : -1, "name" : "--请选择--"},
            {"value": 9, "name": "杭州大厦"},
            {"value": 20, "name": "杭州银泰"},
            {"value": 73, "name": "杭州解百"},
            {"value": 122, "name": "杭州西湖银泰"},
            {"value": 223, "name": "杭州萧山银隆"}]
    },
    {
        "cid" : "0572",
        "cname" : "湖州",
        "list" : [
            {"value": 156, "name": "湖州浙北"}]
    },
    {
        "cid" : "0573",
        "cname" : "嘉兴",
        "list" : [
            {"value": 209, "name": "嘉兴江南"}]
    },
    {
        "cid" : "0574",
        "cname" : "宁波",
        "list" : [
            {"value" : -1, "name" : "--请选择--"},
            {"value": 32, "name": "宁波银泰"},
            {"value": 198, "name": "宁波鄞州银泰"}]
    },
    {
        "cid" : "0575",
        "cname" : "绍兴",
        "list" : [
            {"value": 153, "name": "绍兴国商"}]
    },
    {
        "cid" : "0577",
        "cname" : "温州",
        "list" : [
            {"value" : -1, "name" : "--请选择--"},
            {"value": 35, "name": "温州开太"},
            {"value": 68, "name": "温州时代"},
            {"value": 145, "name": "温州银泰"}]
    },
    {
        "cid" : "0579",
        "cname" : "金华",
        "list" : [
            {"value": 140, "name": "金华一百"}]
    },
    {
        "cid" : "023",
        "cname" : "重庆",
        "list" : [
            {"value" : -1, "name" : "--请选择--"},
            {"value": 11, "name": "重庆太平洋"},
            {"value": 39, "name": "重庆远东"},
            {"value": 120, "name": "重庆新世纪"},
            {"value": 186, "name": "重庆凯瑞商都"}]
    }
]
}